MANIFEST.in
setup.py
chunky/__init__.py
chunky/admin.py
chunky/decorators.py
chunky/models.py
chunky/tests.py
chunky/urls.py
chunky/views.py
chunky/migrations/0001_initial.py
chunky/migrations/0002_added_basic_model.py
chunky/migrations/__init__.py
chunky/static/chunky.js
chunky/static/ckeditor/CHANGES.md
chunky/static/ckeditor/LICENSE.md
chunky/static/ckeditor/README.md
chunky/static/ckeditor/build-config.js
chunky/static/ckeditor/ckeditor.js
chunky/static/ckeditor/config.js
chunky/static/ckeditor/contents.css
chunky/static/ckeditor/styles.js
chunky/static/ckeditor/lang/en.js
chunky/static/ckeditor/plugins/icons.png
chunky/static/ckeditor/plugins/clipboard/dialogs/paste.js
chunky/static/ckeditor/plugins/dialog/dialogDefinition.js
chunky/static/ckeditor/plugins/fakeobjects/images/spacer.gif
chunky/static/ckeditor/plugins/link/dialogs/anchor.js
chunky/static/ckeditor/plugins/link/dialogs/link.js
chunky/static/ckeditor/plugins/link/images/anchor.png
chunky/static/ckeditor/skins/moono/dialog.css
chunky/static/ckeditor/skins/moono/dialog_ie.css
chunky/static/ckeditor/skins/moono/dialog_ie7.css
chunky/static/ckeditor/skins/moono/dialog_ie8.css
chunky/static/ckeditor/skins/moono/dialog_opera.css
chunky/static/ckeditor/skins/moono/editor.css
chunky/static/ckeditor/skins/moono/editor_gecko.css
chunky/static/ckeditor/skins/moono/editor_ie.css
chunky/static/ckeditor/skins/moono/editor_ie7.css
chunky/static/ckeditor/skins/moono/editor_ie8.css
chunky/static/ckeditor/skins/moono/icons.png
chunky/static/ckeditor/skins/moono/readme.md
chunky/static/ckeditor/skins/moono/images/arrow.png
chunky/static/ckeditor/skins/moono/images/close.png
chunky/static/ckeditor/skins/moono/images/mini.png
chunky/static/js/underscore-min.js
chunky/templates/chunk_template.html
chunky/templates/chunky_js_import.html
chunky/templatetags/__init__.py
chunky/templatetags/chunk.py
django_chunky.egg-info/PKG-INFO
django_chunky.egg-info/SOURCES.txt
django_chunky.egg-info/dependency_links.txt
django_chunky.egg-info/not-zip-safe
django_chunky.egg-info/top_level.txt