Metadata-Version: 1.0
Name: django-chunky
Version: 0.1.7
Summary: Editable content chunks for Django
Home-page: http://github.com/freyley/django-chunky
Author: Chris Pitzer, Jeff Schwaber, LoFi Art
Author-email: freyley@gmail.com
License: UNKNOWN
Platform: UNKNOWN
Classifier: Development Status :: 3 - Alpha
Classifier: Environment :: Web Environment
Classifier: Intended Audience :: Developers
Classifier: License :: OSI Approved :: BSD License
Classifier: Operating System :: OS Independent
Classifier: Programming Language :: Python
Classifier: Framework :: Django
